hfppl/__init__.py
hfppl/chunks.py
hfppl/distributions/__init__.py
hfppl/distributions/bernoulli.py
hfppl/distributions/distribution.py
hfppl/distributions/geometric.py
hfppl/distributions/lmcontext.py
hfppl/distributions/logcategorical.py
hfppl/distributions/tokencategorical.py
hfppl/distributions/transformer.py
hfppl/inference/__init__.py
hfppl/inference/smc_record.py
hfppl/inference/smc_standard.py
hfppl/inference/smc_steer.py
hfppl/llms.py
hfppl/modeling.py
hfppl/util.py
hfppl-0.1.2.dist-info/METADATA
hfppl-0.1.2.dist-info/WHEEL
hfppl-0.1.2.dist-info/RECORD
