Metadata-Version: 2.3
Name: hfppl
Version: 0.1.2
Summary: Deprecated. Please use 'llamppl' instead.
License: MIT
Author: Alex Lew
Author-email: alexlew@mit.edu
Requires-Python: >=3.10,<4.0
Classifier: License :: OSI Approved :: MIT License
Classifier: Programming Language :: Python :: 3
Classifier: Programming Language :: Python :: 3.10
Classifier: Programming Language :: Python :: 3.11
Classifier: Programming Language :: Python :: 3.12
Classifier: Programming Language :: Python :: 3.13
Provides-Extra: examples
Requires-Dist: genlm-backend (>=0.0.2,<0.0.3)
Requires-Dist: ipykernel (>=6.29.5,<7.0.0)
Requires-Dist: nltk (>=3.8.1,<4.0.0) ; extra == "examples"
Requires-Dist: numpy (>=1.26.2,<2.0.0)
Requires-Dist: pre-commit (>=3.7.1,<4.0.0)
Requires-Dist: protobuf (>=5.27.2,<6.0.0)
Requires-Dist: scipy (>=1.11.4,<2.0.0)
Requires-Dist: torch (>=2.1.2,<3.0.0)
